LICENSE.txt
MANIFEST.in
README.md
pyproject.toml
setup.py
sibel/__init__.pyi
sibel/py.typed
sibel/sibel.pyi
sibel.egg-info/PKG-INFO
sibel.egg-info/SOURCES.txt
sibel.egg-info/dependency_links.txt
sibel.egg-info/top_level.txt
src/sibel.h
src/sibelmodule.cc
src/simplification.cc
src/substitutions.cc
src/test