Metadata-Version: 2.1
Name: sibel
Version: 0.1.1
Summary: Python spellchecker with Hunspell as back-end
Author-email: Yi Xing <blandilyte@gmail.com>
Project-URL: Homepage, https://github.com/Crissium/sibel
Classifier: Programming Language :: C++
Classifier: License :: OSI Approved :: GNU Lesser General Public License v3 (LGPLv3)
Classifier: Operating System :: OS Independent
Requires-Python: >=3.10
License-File: LICENSE.txt
